sentry_github
